wialon/__init__.py
wialon/api.py
wialon/flags.py
python_wialon-1.2.4.dist-info/LICENSE
python_wialon-1.2.4.dist-info/METADATA
python_wialon-1.2.4.dist-info/WHEEL
python_wialon-1.2.4.dist-info/top_level.txt
python_wialon-1.2.4.dist-info/zip-safe
python_wialon-1.2.4.dist-info/RECORD
