Metadata-Version: 2.1
Name: python-wialon
Version: 1.2.4
Summary: Wialon Remote API wrapper for Python.
Home-page: https://github.com/wialon/python-wialon
Download-URL: http://pypi.python.org/pypi/python-wialon/
Author: Alex Chernetsky chal@gurtam.com
Keywords: wialon remote api wrapper
Classifier: Development Status :: 5 - Production/Stable
Classifier: Intended Audience :: Developers
Classifier: License :: OSI Approved :: MIT License
Classifier: Natural Language :: English
Classifier: Operating System :: OS Independent
Classifier: Programming Language :: Python
Classifier: Topic :: Software Development :: Libraries :: Python Modules
License-File: LICENSE
Requires-Dist: simplejson
Requires-Dist: future
